sillyorm/__init__.py
sillyorm/environment.py
sillyorm/exceptions.py
sillyorm/fields.py
sillyorm/migration_helpers.py
sillyorm/model.py
sillyorm/registry.py
sillyorm-1.0.0.dist-info/licenses/LICENSE
sillyorm-1.0.0.dist-info/METADATA
sillyorm-1.0.0.dist-info/WHEEL
sillyorm-1.0.0.dist-info/top_level.txt
sillyorm-1.0.0.dist-info/RECORD
