Metadata-Version: 2.4
Name: sillyORM
Version: 1.0.0
Summary: an ORM library
License:                    GNU LESSER GENERAL PUBLIC LICENSE
Requires-Python: >=3.11
License-File: LICENSE
Requires-Dist: alembic~=1.15.2
Requires-Dist: sqlalchemy~=2.0.40
Provides-Extra: dev
Requires-Dist: pytest; extra == "dev"
Requires-Dist: coverage; extra == "dev"
Requires-Dist: pylint; extra == "dev"
Requires-Dist: mypy; extra == "dev"
Requires-Dist: black; extra == "dev"
Requires-Dist: Sphinx; extra == "dev"
Dynamic: license-file
